marleu_pytest/__init__.py
marleu_pytest/entrypoint.py
marleu_pytest/greetings/__init__.py
marleu_pytest/greetings/bad.py
marleu_pytest/greetings/good.py
marleu_pytest-0.1.2.dist-info/entry_points.txt
marleu_pytest-0.1.2.dist-info/WHEEL
marleu_pytest-0.1.2.dist-info/METADATA
marleu_pytest-0.1.2.dist-info/RECORD
