Metadata-Version: 2.1
Name: marleu-pytest
Version: 0.1.2
Summary: 
Author: Martin Leuthold
Requires-Python: >=3.7,<4.0
Classifier: Programming Language :: Python :: 3
Classifier: Programming Language :: Python :: 3.7
Classifier: Programming Language :: Python :: 3.8
Classifier: Programming Language :: Python :: 3.9
Requires-Dist: click
